examples/__init__.py
examples/image_augmentation.py
examples/overlaying_mask.py
examples/pygame_simulator.py
examples/pygame_video_simulator.py
examples/server.py
examples/video_augmentation.py
smokesim/__init__.py
smokesim/augmentation.py
smokesim/base.py
smokesim/engine.py
smokesim/noise.py
smokesim/particle.py
smokesim/smoke.py
smokesim/vis.py
smokesim/defs/__init__.py
smokesim/defs/constants.py
smokesim/defs/particle.py
smokesim/defs/smoke.py
smokesim-0.0.32.dist-info/LICENSE
smokesim-0.0.32.dist-info/METADATA
smokesim-0.0.32.dist-info/WHEEL
smokesim-0.0.32.dist-info/top_level.txt
smokesim-0.0.32.dist-info/RECORD
