Metadata-Version: 2.1
Name: smokesim
Version: 0.0.32
Summary: A package for doing smoke simulation.
Home-page: https://github.com/q-viper/SmokeSim
Author: Ramkrishna Acharya(QViper)
Author-email: qramkrishna@gmail.com
Keywords: smoke,simulation
Classifier: License :: OSI Approved :: Apache Software License
Classifier: Programming Language :: Python
Classifier: Programming Language :: Python :: 3.8
Classifier: Programming Language :: Python :: 3.9
Classifier: Programming Language :: Python :: 3.10
Classifier: Development Status :: 4 - Beta
Classifier: Intended Audience :: Developers
Classifier: Topic :: Software Development :: Libraries :: Python Modules
License-File: LICENSE
Requires-Dist: numpy<2
Requires-Dist: pygame==2.6.1
Requires-Dist: pygame-gui==0.6.9
Requires-Dist: black==24.4.2
Requires-Dist: pydantic==2.7.1
Requires-Dist: opencv-python<4.10.0
Requires-Dist: pillow
